README.md
setup.py
feishuapi/__init__.py
feishuapi.egg-info/PKG-INFO
feishuapi.egg-info/SOURCES.txt
feishuapi.egg-info/dependency_links.txt
feishuapi.egg-info/not-zip-safe
feishuapi.egg-info/top_level.txt
feishuapi/larkcustombot/__init__.py
feishuapi/larkcustombot/larkcustombot.py
feishuapi/larkcustombot/post.py