Metadata-Version: 2.1
Name: feishuapi
Version: 0.0.8
Summary: Python feishu API SDK
Home-page: https://github.com/mrchenxxx/FeiShuAPI
Author: taitai
Author-email: 834482351@qq.com
License: MIT
Keywords: python-feishu,feishu,lark,飞书
